entsoe/__init__.py
entsoe/Balancing/__init__.py
entsoe/Balancing/specific_params.py
entsoe/Base/Balancing.py
entsoe/Base/Base.py
entsoe/Base/Generation.py
entsoe/Base/Load.py
entsoe/Base/Market.py
entsoe/Base/Outages.py
entsoe/Base/Transmission.py
entsoe/Generation/__init__.py
entsoe/Generation/specific_params.py
entsoe/Load/__init__.py
entsoe/Load/specific_params.py
entsoe/Market/__init__.py
entsoe/Market/specific_params.py
entsoe/MasterData/__init__.py
entsoe/MasterData/specific_params.py
entsoe/OMI/OMI.py
entsoe/OMI/__init__.py
entsoe/OMI/specific_params.py
entsoe/Outages/__init__.py
entsoe/Outages/specific_params.py
entsoe/Transmission/__init__.py
entsoe/Transmission/specific_params.py
entsoe/codes/__init__.py
entsoe/codes/codes.py
entsoe/config/__init__.py
entsoe/config/config.py
entsoe/query/decorators.py
entsoe/query/query_api.py
entsoe/utils/__init__.py
entsoe/utils/mappings_dict.py
entsoe/utils/records.py
entsoe/utils/timestamps.py
entsoe/utils/utils.py
entsoe/xml_models/__init__.py
entsoe/xml_models/iec62325_451_1_acknowledgement_v7_0.py
entsoe/xml_models/iec62325_451_1_acknowledgement_v8_0.py
entsoe/xml_models/iec62325_451_1_acknowledgement_v8_1.py
entsoe/xml_models/iec62325_451_1_acknowledgement_v9_0.py
entsoe/xml_models/iec62325_451_2_anomaly_v5_0.py
entsoe/xml_models/iec62325_451_2_anomaly_v5_1.py
entsoe/xml_models/iec62325_451_2_anomaly_v5_2.py
entsoe/xml_models/iec62325_451_2_anomaly_v5_3.py
entsoe/xml_models/iec62325_451_2_confirmation_v5_0.py
entsoe/xml_models/iec62325_451_2_confirmation_v5_1.py
entsoe/xml_models/iec62325_451_2_confirmation_v5_2.py
entsoe/xml_models/iec62325_451_2_confirmation_v5_3.py
entsoe/xml_models/iec62325_451_2_schedule_v5_0.py
entsoe/xml_models/iec62325_451_2_schedule_v5_1.py
entsoe/xml_models/iec62325_451_2_schedule_v5_2.py
entsoe/xml_models/iec62325_451_3_allocation_v7_0.py
entsoe/xml_models/iec62325_451_3_allocation_v7_1.py
entsoe/xml_models/iec62325_451_3_allocation_v7_2.py
entsoe_apy-0.9.0.dist-info/licenses/LICENSE
entsoe_apy-0.9.0.dist-info/METADATA
entsoe_apy-0.9.0.dist-info/WHEEL
entsoe_apy-0.9.0.dist-info/top_level.txt
entsoe_apy-0.9.0.dist-info/RECORD
