Metadata-Version: 2.4
Name: entsoe-apy
Version: 0.9.0
Summary: A Python library for accessing ENTSO-E Transparency Platform API endpoints
Author-email: Jonathan Berrisch <jonathan.berrisch@uni-due.de>, Jie Xu <jie.xu@uni-due.de>
License-Expression: GPL-3.0-or-later
Project-URL: Homepage, https://entsoe-apy.berrisch.biz/
Project-URL: Documentation, https://entsoe-apy.berrisch.biz/
Project-URL: Repository, https://github.com/BerriJ/entsoe-api-py
Project-URL: Bug Tracker, https://github.com/BerriJ/entsoe-api-py/issues
Keywords: entsoe,energy,electricity,api,transparency,platform
Classifier: Development Status :: 4 - Beta
Classifier: Intended Audience :: Developers
Classifier: Intended Audience :: Science/Research
Classifier: Operating System :: OS Independent
Classifier: Programming Language :: Python :: 3
Classifier: Programming Language :: Python :: 3.11
Classifier: Programming Language :: Python :: 3.12
Classifier: Programming Language :: Python :: 3.13
Classifier: Topic :: Scientific/Engineering
Classifier: Topic :: Software Development :: Libraries :: Python Modules
Requires-Python: <3.15.0,>=3.11.0
License-File: LICENSE
Requires-Dist: httpx~=0.28.1
Requires-Dist: loguru~=0.7.2
Requires-Dist: xsdata-pydantic>=24.5
Requires-Dist: isodate>=0.7.2
Dynamic: license-file
